LICENSE
MANIFEST.in
README.md
requirements.txt
setup.py
cyw_bogus.egg-info/PKG-INFO
cyw_bogus.egg-info/SOURCES.txt
cyw_bogus.egg-info/dependency_links.txt
cyw_bogus.egg-info/entry_points.txt
cyw_bogus.egg-info/requires.txt
cyw_bogus.egg-info/top_level.txt
foobar/__init__.py
foobar/admin.py
foobar/models.py
foobar/tests.py
foobar/views.py
foobar/migrations/__init__.py
otree/__init__.py
otree/apps.py
otree/common.py
otree/common_internal.py
otree/constants.py
otree/constants_internal.py
otree/context_processors.py
otree/default_urls.py
otree/deprecate.py
otree/match_players.py
otree/middleware.py
otree/models_concrete.py
otree/serializers.py
otree/session.py
otree/settings.py
otree/signals.py
otree/urls.py
otree/widgets.py
otree/wsgi.py
otree/app_template/__init__.py
otree/app_template/models.py
otree/app_template/tests.py
otree/app_template/views.py
otree/app_template/_builtin/__init__.py
otree/app_template/templates/app_name/MyPage.html
otree/app_template/templates/app_name/Results.html
otree/celery/__init__.py
otree/celery/app.py
otree/celery/setup.py
otree/checks/__init__.py
otree/checks/mturk.py
otree/checks/templates.py
otree/db/__init__.py
otree/db/models.py
otree/forms/__init__.py
otree/forms/fields.py
otree/forms/forms.py
otree/forms/widgets.py
otree/locale/de/LC_MESSAGES/django.mo
otree/locale/de/LC_MESSAGES/django.po
otree/locale/es/LC_MESSAGES/django.mo
otree/locale/es/LC_MESSAGES/django.po
otree/locale/fr/LC_MESSAGES/django.mo
otree/locale/fr/LC_MESSAGES/django.po
otree/locale/hu/LC_MESSAGES/django.mo
otree/locale/hu/LC_MESSAGES/django.po
otree/locale/it/LC_MESSAGES/django.mo
otree/locale/it/LC_MESSAGES/django.po
otree/locale/ja/LC_MESSAGES/django.mo
otree/locale/ja/LC_MESSAGES/django.po
otree/locale/ko/LC_MESSAGES/django.mo
otree/locale/ko/LC_MESSAGES/django.po
otree/locale/ru/LC_MESSAGES/django.mo
otree/locale/ru/LC_MESSAGES/django.po
otree/locale/zh_CN/LC_MESSAGES/django.mo
otree/locale/zh_CN/LC_MESSAGES/django.po
otree/management/__init__.py
otree/management/cli.py
otree/management/commands/__init__.py
otree/management/commands/create_session.py
otree/management/commands/resetdb.py
otree/management/commands/runprodserver.py
