Metadata-Version: 1.1
Name: cyw-bogus
Version: 0.4.24
Summary: oTree is a toolset that makes it easy to create and administer web-based social science experiments.
Home-page: http://otree.org/
Author: C. Wickens
Author-email: c.wickens+otree@googlemail.com
License: MIT License
Platform: UNKNOWN
Classifier: Environment :: Web Environment
Classifier: Framework :: Django
Classifier: Intended Audience :: Developers
Classifier: License :: OSI Approved :: MIT License
Classifier: Operating System :: OS Independent
Classifier: Programming Language :: Python
Classifier: Programming Language :: Python :: 2
Classifier: Programming Language :: Python :: 2.7
Classifier: Topic :: Internet :: WWW/HTTP
Classifier: Topic :: Internet :: WWW/HTTP :: Dynamic Content
